shap_selection/__init__.py
shap_selection/feature_selection.py
shap_selection-0.1.6.dist-info/LICENSE
shap_selection-0.1.6.dist-info/METADATA
shap_selection-0.1.6.dist-info/WHEEL
shap_selection-0.1.6.dist-info/top_level.txt
shap_selection-0.1.6.dist-info/RECORD
