Metadata-Version: 2.1
Name: shap-selection
Version: 0.1.6
Summary: Selecting features using SHAP values
Home-page: https://github.com/wilsonjr/SHAP_FSelection
Author: Wilson Estecio Marcilio Junior
Author-email: wilson_jr@outlook.com
License: MIT
Platform: UNKNOWN
License-File: LICENSE
Requires-Dist: shap
Requires-Dist: numpy
